laydata/__init__.py
laydata/attachment_item.py
laydata/base.py
laydata/connection.py
laydata/data.py
laydata/query.py
laydata/record.py
laydata/space.py
laydata/table.py
laydata/types.py
laydata-0.1.8.dist-info/METADATA
laydata-0.1.8.dist-info/WHEEL
laydata-0.1.8.dist-info/top_level.txt
laydata-0.1.8.dist-info/RECORD
