Metadata-Version: 2.4
Name: laydata
Version: 0.1.8
Summary: LayData Python SDK
Requires-Python: >=3.10
Requires-Dist: laydata-core
Requires-Dist: httpx[http2]>=0.25.0
Requires-Dist: typing-extensions>=4.0.0
